saferates/__init__.py
saferates/account.py
saferates/antispam.py
saferates/api.py
saferates/audit.py
saferates/backup.py
saferates/channels.py
saferates/commands.py
saferates/dms.py
saferates/embeds.py
saferates/emojis.py
saferates/events.py
saferates/export.py
saferates/friends.py
saferates/guilds.py
saferates/history.py
saferates/invites.py
saferates/logger.py
saferates/messaging.py
saferates/moderator.py
saferates/nitro.py
saferates/onliner.py
saferates/polls.py
saferates/presence.py
saferates/reactions.py
saferates/reminders.py
saferates/roles.py
saferates/stickers.py
saferates/user.py
saferates/utils.py
saferates/voice.py
saferates/webhook.py
saferates/welcome.py
saferates-0.3.5.dist-info/METADATA
saferates-0.3.5.dist-info/WHEEL
saferates-0.3.5.dist-info/top_level.txt
saferates-0.3.5.dist-info/RECORD
