Metadata-Version: 2.1
Name: saferates
Version: 0.3.5
Summary: Discord API toolkit for user tokens with token onliner functionality (selfbot use mainly).
Author-email: DriizzyyB <driizzyyboosts@gmail.com>
Requires-Python: >=3.8
Requires-Dist: httpx >=0.25.0
